MANIFEST.in
README.md
setup.py
defgen/__init__.py
defgen/generation.py
defgen.egg-info/PKG-INFO
defgen.egg-info/SOURCES.txt
defgen.egg-info/dependency_links.txt
defgen.egg-info/requires.txt
defgen.egg-info/top_level.txt
defgen/static/templates_auto/0/index.html
defgen/static/templates_auto/0/main.css