Metadata-Version: 2.1
Name: defgen
Version: 0.0.16
Summary: Tool to create stylish definitions from structured input
Home-page: https://github.com/Outige/definition-generator
Author: Tieg O'Sullivan
Author-email: tiegosullivanpsnl@gmail.com
License: MIT
Platform: UNKNOWN
Classifier: License :: OSI Approved :: MIT License
Classifier: Programming Language :: Python :: 3
Classifier: Programming Language :: Python :: 3.8
